MANIFEST.in
PYPI-DESC.md
README.md
setup.py
opsbot/__init__.py
opsbot/constant.py
opsbot/devopshelper.py
opsbot/opsbot.py
opsbot.egg-info/PKG-INFO
opsbot.egg-info/SOURCES.txt
opsbot.egg-info/dependency_links.txt
opsbot.egg-info/entry_points.txt
opsbot.egg-info/top_level.txt
opsbot/template/.gitignore.template
opsbot/template/.opsbot.template
opsbot/template/opsbot_generated.sh.template
opsbot/template/passwordgenerated.sh
opsbot/template/env/angular.sh
opsbot/template/env/common.sh
opsbot/template/env/composer.sh
opsbot/template/env/https.sh
opsbot/template/env/lamp.sh
opsbot/template/env/mongodb.sh
opsbot/template/env/node.sh
opsbot/template/env/scrapy.sh
opsbot/template/env/sshkeygen.sh
opsbot/template/fix/mysql-change-root-auth-type.sh
opsbot/template/fix/phpmyadmin-upgrade-48.sh
opsbot/template/global-tool/certbotsafe.sh
opsbot/template/global-tool/dbbackup.sh
opsbot/template/global-tool/dbdump.sh
opsbot/template/global-tool/sourcebackup.sh
opsbot/template/site/mkdir.sh
opsbot/template/site/vhost-proxy.sh
opsbot/template/site/vhost.sh
opsbot/template/site-tool/configgenerated
opsbot/template/site-tool/dbexport.sh
opsbot/template/site-tool/dbimport.sh
opsbot/template/site-tool/deploysite.sh
opsbot/template/site-tool/resetowner.sh
opsbot/template/user/mongodb.sh
opsbot/template/user/mysql.sh
opsbot/template/user/unix.sh
opsbot/template/util/make_all_normal_user_can_sudo_global_tool.sh
opsbot/template/util/make_global_tool.sh
opsbot/template/util/make_owner_can_sudo_site_tool.sh
opsbot/template/util/make_run_daily.sh
opsbot/template/util/make_site_tool.sh