Metadata-Version: 1.1
Name: opsbot
Version: 20.10.45
Summary: I'm Opsbot. I can help you create the best devops scripts.
Home-page: https://gitlab.com/magiklab/opsbot-py
Author: Diep Magik
Author-email: diepnh@magik.vn
License: MIT
Platform: UNKNOWN
Classifier: Development Status :: 3 - Alpha
Classifier: Intended Audience :: Developers
Classifier: Topic :: Software Development :: Build Tools
Classifier: Topic :: System :: Operating System
Classifier: Topic :: System :: Shells
Classifier: License :: OSI Approved :: MIT License
Classifier: Programming Language :: Python :: 2
Classifier: Programming Language :: Python :: 2.6
Classifier: Programming Language :: Python :: 2.7
